base_template_cli/__init__.py
base_template_cli/applyer.py
base_template_cli/base_template_updater.py
base_template_cli/di_manager.py
base_template_cli/file_copy_util.py
base_template_cli/main.py
base_template_cli/version_getter.py
base_template_cli-3.0.2.dist-info/METADATA
base_template_cli-3.0.2.dist-info/WHEEL
base_template_cli-3.0.2.dist-info/entry_points.txt
base_template_cli-3.0.2.dist-info/licenses/LICENSE
base_template_cli-3.0.2.dist-info/RECORD
