Metadata-Version: 2.1
Name: base-template-cli
Version: 3.0.2
Summary: CLI tool of Base Template Repository.
Project-URL: Homepage, https://github.com/haru52/base_template_cli#readme
Project-URL: Bug Tracker, https://github.com/haru52/base_template_cli/issues
Project-URL: Repository, https://github.com/haru52/base_template_cli.git
Author: haru
License-Expression: MIT
License-File: LICENSE
Keywords: base-template,cli,template
Classifier: License :: OSI Approved :: MIT License
Classifier: Operating System :: OS Independent
Classifier: Programming Language :: Python :: 3
Requires-Python: ~=3.11
Requires-Dist: click~=8.1
